{
  "schemaVersion": "1.1.0",
  "id": "labor-force-participation",
  "providerCode": "SL.TLF.CACT.ZS",
  "title": "Labor force participation rate, total (% of total population ages 15+) (modeled ILO estimate)",
  "shortTitle": "Labor force participation",
  "category": "labor",
  "difficulty": "standard",
  "definition": "Labor force participation rate is the proportion of the population ages 15 and older that is economically active: all people who supply labor for the production of goods and services during a specified period.",
  "unit": "percent ages 15+",
  "year": 2025,
  "valuesByIso3": {
    "AFG": 37.457,
    "AGO": 74.786,
    "ALB": 64.263,
    "ARE": 78.594,
    "ARG": 61.913,
    "ARM": 59.388,
    "AUS": 66.537,
    "AUT": 60.124,
    "AZE": 63.288,
    "BDI": 78.255,
    "BEL": 54.274,
    "BEN": 76.356,
    "BFA": 70.005,
    "BGD": 58.796,
    "BGR": 56.115,
    "BHS": 73.775,
    "BIH": 48.991,
    "BLR": 62.747,
    "BLZ": 59.1,
    "BOL": 78.626,
    "BRA": 63.139,
    "BRN": 64.235,
    "BTN": 64.82,
    "BWA": 68.798,
    "CAF": 73.389,
    "CAN": 64.516,
    "CHE": 66.747,
    "CHL": 62.304,
    "CHN": 64.551,
    "CIV": 67.09,
    "CMR": 65.171,
    "COD": 64.306,
    "COG": 67.825,
    "COL": 63.398,
    "CRI": 57.659,
    "CUB": 52.248,
    "CYP": 66.961,
    "CZE": 60.341,
    "DEU": 60.571,
    "DJI": 31.744,
    "DNK": 64.935,
    "DOM": 64.839,
    "DZA": 40.784,
    "ECU": 64.497,
    "EGY": 44.568,
    "ERI": 78.348,
    "ESP": 57.41,
    "EST": 65.128,
    "ETH": 68.461,
    "FIN": 59.681,
    "FJI": 57.16,
    "FRA": 55.346,
    "GAB": 51.058,
    "GBR": 61.369,
    "GEO": 64.312,
    "GHA": 58.524,
    "GIN": 52.61,
    "GMB": 47.457,
    "GNB": 64.814,
    "GNQ": 60.513,
    "GRC": 51.958,
    "GTM": 59.619,
    "GUY": 54.987,
    "HND": 56.556,
    "HRV": 52.143,
    "HTI": 63.93,
    "HUN": 60.578,
    "IDN": 67.965,
    "IND": 55.658,
    "IRL": 64.844,
    "IRN": 40.965,
    "IRQ": 41.533,
    "ISL": 74.926,
    "ISR": 65.489,
    "ITA": 49.302,
    "JAM": 69.566,
    "JOR": 40.052,
    "JPN": 63.448,
    "KAZ": 67.77,
    "KEN": 67.385,
    "KGZ": 57.366,
    "KHM": 82.392,
    "KOR": 64.351,
    "KWT": 73.365,
    "LAO": 66.087,
    "LBR": 76.582,
    "LBY": 47.963,
    "LKA": 48.517,
    "LSO": 57.117,
    "LTU": 62.918,
    "LUX": 61.502,
    "LVA": 60.519,
    "MAR": 43.941,
    "MDA": 72.29,
    "MDG": 85.495,
    "MEX": 61.609,
    "MKD": 51.935,
    "MLI": 67.036,
    "MMR": 55.088,
    "MNE": 57.966,
    "MNG": 59.689,
    "MOZ": 78.709,
    "MRT": 40.772,
    "MWI": 62.577,
    "MYS": 66.12,
    "NAM": 58.838,
    "NCL": 56.421,
    "NER": 79.741,
    "NGA": 82.517,
    "NIC": 66.074,
    "NLD": 67.248,
    "NOR": 65.606,
    "NPL": 39.244,
    "NZL": 70.352,
    "OMN": 68.377,
    "PAK": 52.335,
    "PAN": 66.304,
    "PER": 72.856,
    "PHL": 61.35,
    "PNG": 52.07,
    "POL": 58.312,
    "PRI": 42.779,
    "PRK": 82.152,
    "PRT": 58.161,
    "PRY": 70.247,
    "QAT": 87.013,
    "ROU": 51.331,
    "RUS": 61.113,
    "RWA": 63.681,
    "SAU": 65.098,
    "SEN": 52.019,
    "SLB": 84.296,
    "SLE": 53.372,
    "SLV": 62.107,
    "SOM": 33.846,
    "SRB": 59.142,
    "SUR": 53.823,
    "SVK": 60.422,
    "SVN": 57.565,
    "SWE": 64.595,
    "SWZ": 51.191,
    "SYR": 36.898,
    "TCD": 59.44,
    "TGO": 57.845,
    "THA": 66.678,
    "TJK": 38.276,
    "TKM": 42.031,
    "TLS": 66.98,
    "TTO": 57.75,
    "TUN": 45.219,
    "TUR": 54.379,
    "TZA": 83.716,
    "UGA": 80.028,
    "URY": 64.99,
    "USA": 61.704,
    "UZB": 57.499,
    "VEN": 51.927,
    "VNM": 72.778,
    "VUT": 58.111,
    "YEM": 33.103,
    "ZAF": 55.584,
    "ZMB": 61.933,
    "ZWE": 67.718
  },
  "stats": {
    "coverage": 163,
    "min": 31.744,
    "max": 87.013,
    "median": 61.704,
    "quantileBreaks": [
      31.744,
      51.211000000000006,
      57.129285714285714,
      60.217,
      63.58114285714286,
      66.08328571428572,
      72.01314285714287,
      87.013
    ]
  },
  "formatting": {
    "maximumFractionDigits": 1,
    "suffix": "%"
  },
  "source": {
    "provider": "World Bank",
    "dataset": "World Development Indicators",
    "attribution": "The World Bank",
    "sourceReference": "https://api.worldbank.org/v2/indicator/SL.TLF.CACT.ZS?format=json&per_page=1",
    "valuesReference": "https://api.worldbank.org/v2/country/all/indicator/SL.TLF.CACT.ZS?format=json&per_page=20000&page=1&date=2015%3A2025",
    "license": "Creative Commons Attribution 4.0 International unless specifically labeled otherwise by World Bank metadata",
    "licenseReference": "https://www.worldbank.org/en/about/legal/terms-of-use-for-datasets",
    "retrievedAt": "2026-07-02T22:13:49.837706+00:00",
    "checksum": "24b59a15bb6a5c226933bd0e3b4f6b966acaa9d03cea91adc12d9ee9b106fc06",
    "sourceOrganization": "ILO Modelled Estimates database (ILOEST), International Labour Organization (ILO), uri: https://ilostat.ilo.org/data/bulk/, publisher: ILOSTAT, type: external database, date accessed: January 17, 2026"
  },
  "reviewStatus": "approved",
  "contentVersion": "2026.07.02-exp4-content50",
  "editorial": {
    "shortHook": "A map of who is counted in the labor force.",
    "patternNote": "The darkest countries include Qatar, Madagascar, Solomon Islands, while the lightest include Djibouti, Yemen, Rep., Somalia, Fed. Rep.; that contrast is the fastest way to read the labor force participation pattern.",
    "whyItMatters": "Participation helps separate joblessness from whether adults are seeking or doing paid work.",
    "bestProbeCountries": [
      {
        "iso3": "QAT",
        "reason": "High anchor: this country sits near the darkest end of the map."
      },
      {
        "iso3": "DJI",
        "reason": "Low anchor: this country clarifies the lightest end of the scale."
      },
      {
        "iso3": "USA",
        "reason": "Middle check: this country helps separate a true pattern from one-off outliers."
      }
    ],
    "commonConfusions": [
      {
        "confusedWithIndicatorCode": "SL.EMP.TOTL.SP.ZS",
        "reason": "Employment-to-population ratio can tempt players because it shares a strong country ranking with this map, but its unit and definition point to a different story."
      },
      {
        "confusedWithIndicatorCode": "SL.EMP.TOTL.SP.FE.ZS",
        "reason": "Female employment-to-population ratio can tempt players because it shares a strong country ranking with this map, but its unit and definition point to a different story."
      },
      {
        "confusedWithIndicatorCode": "SL.TLF.CACT.FE.ZS",
        "reason": "Female labor force participation can tempt players because it shares a strong country ranking with this map, but its unit and definition point to a different story."
      }
    ],
    "difficultyReason": "Standard difficulty: the map has readable regional structure, but the best answer still depends on checking the unit and country anchors.",
    "regionalSignals": [
      "Labor maps often reveal sector structure and gender participation differences.",
      "Compare agriculture-heavy and service-heavy economies."
    ]
  },
  "editorialReview": {
    "status": "practice_eligible",
    "reviewedAt": "2026-07-02",
    "reviewedBy": "Codex editorial QA",
    "qualityScore": 3,
    "funScore": 3,
    "fairnessScore": 4,
    "ambiguityRisk": "medium",
    "dailyEligible": false,
    "practiceEligible": true,
    "challengeEligible": true,
    "expertOnly": false,
    "reviewNotes": [
      "Useful labor concept but less visually memorable than unemployment or agricultural employment.",
      "Practice-only for now."
    ],
    "acceptableCloseDistractorIds": []
  }
}
