{
  "schemaVersion": "1.1.0",
  "id": "migrant-stock",
  "providerCode": "SM.POP.TOTL.ZS",
  "title": "International migrant stock (% of population)",
  "shortTitle": "International migrant stock",
  "category": "demography",
  "difficulty": "standard",
  "definition": "International migrant stock (% of population) is the proportion of people at mid-year born in a country other than that in which they live. It also includes refugees.",
  "unit": "percent of population",
  "year": 2024,
  "valuesByIso3": {
    "AFG": 0.2,
    "AGO": 1.8,
    "ALB": 1.7,
    "ARE": 74.0,
    "ARG": 4.3,
    "ARM": 9.2,
    "AUS": 30.4,
    "AUT": 25.5,
    "AZE": 2.1,
    "BDI": 2.8,
    "BEL": 20.0,
    "BEN": 2.9,
    "BFA": 3.1,
    "BGD": 1.7,
    "BGR": 4.4,
    "BHS": 16.8,
    "BIH": 1.1,
    "BLR": 11.6,
    "BLZ": 16.5,
    "BOL": 1.5,
    "BRA": 0.7,
    "BRN": 25.9,
    "BTN": 7.0,
    "BWA": 4.6,
    "CAF": 1.8,
    "CAN": 22.2,
    "CHE": 31.1,
    "CHL": 7.8,
    "CHN": 0.1,
    "CIV": 9.0,
    "CMR": 2.2,
    "COD": 1.0,
    "COG": 6.1,
    "COL": 5.8,
    "CRI": 12.2,
    "CUB": 0.0,
    "CYP": 14.9,
    "CZE": 9.5,
    "DEU": 19.8,
    "DJI": 10.8,
    "DNK": 14.2,
    "DOM": 6.5,
    "DZA": 0.6,
    "ECU": 4.1,
    "EGY": 1.0,
    "ERI": 0.4,
    "ESP": 18.5,
    "EST": 14.9,
    "ETH": 0.9,
    "FIN": 9.2,
    "FJI": 1.5,
    "FRA": 13.8,
    "GAB": 17.7,
    "GBR": 17.1,
    "GEO": 2.1,
    "GHA": 1.5,
    "GIN": 0.8,
    "GMB": 8.6,
    "GNB": 0.7,
    "GNQ": 13.2,
    "GRC": 14.2,
    "GRL": 10.4,
    "GTM": 0.5,
    "GUY": 6.5,
    "HND": 0.4,
    "HRV": 13.6,
    "HTI": 0.2,
    "HUN": 7.1,
    "IDN": 0.2,
    "IND": 0.3,
    "IRL": 23.1,
    "IRN": 4.2,
    "IRQ": 0.8,
    "ISL": 25.1,
    "ISR": 22.3,
    "ITA": 11.0,
    "JAM": 0.8,
    "JOR": 45.7,
    "JPN": 2.8,
    "KAZ": 10.1,
    "KEN": 1.8,
    "KGZ": 2.7,
    "KHM": 0.5,
    "KOR": 3.5,
    "KWT": 67.3,
    "LAO": 0.7,
    "LBN": 24.5,
    "LBR": 1.3,
    "LBY": 12.2,
    "LKA": 0.2,
    "LSO": 0.6,
    "LTU": 6.1,
    "LUX": 51.2,
    "LVA": 11.8,
    "MAR": 0.3,
    "MDA": 6.2,
    "MDG": 0.1,
    "MEX": 1.3,
    "MKD": 8.3,
    "MLI": 2.2,
    "MMR": 0.1,
    "MNE": 14.4,
    "MNG": 0.6,
    "MOZ": 1.0,
    "MRT": 3.8,
    "MWI": 0.9,
    "MYS": 10.7,
    "NAM": 3.8,
    "NCL": 26.2,
    "NER": 1.7,
    "NGA": 0.6,
    "NIC": 0.6,
    "NLD": 16.2,
    "NOR": 18.2,
    "NPL": 1.6,
    "NZL": 28.2,
    "OMN": 43.2,
    "PAK": 1.7,
    "PAN": 10.6,
    "PER": 5.4,
    "PHL": 0.1,
    "PNG": 0.3,
    "POL": 4.5,
    "PRI": 6.9,
    "PRK": 0.2,
    "PRT": 10.8,
    "PRY": 2.6,
    "PSE": 5.0,
    "QAT": 76.7,
    "ROU": 3.4,
    "RUS": 5.3,
    "RWA": 3.6,
    "SAU": 40.3,
    "SDN": 4.8,
    "SEN": 1.5,
    "SLB": 0.3,
    "SLE": 0.6,
    "SLV": 0.7,
    "SOM": 0.4,
    "SRB": 10.6,
    "SSD": 7.7,
    "SUR": 8.2,
    "SVK": 5.9,
    "SVN": 14.9,
    "SWE": 21.4,
    "SWZ": 2.7,
    "SYR": 3.6,
    "TCD": 6.3,
    "TGO": 3.0,
    "THA": 4.4,
    "TJK": 2.6,
    "TKM": 2.6,
    "TLS": 0.6,
    "TTO": 7.5,
    "TUN": 0.5,
    "TUR": 8.1,
    "TZA": 0.7,
    "UGA": 4.1,
    "UKR": 13.4,
    "URY": 4.7,
    "USA": 15.2,
    "UZB": 3.2,
    "VEN": 4.4,
    "VNM": 0.3,
    "VUT": 1.0,
    "YEM": 1.0,
    "ZAF": 4.1,
    "ZMB": 1.2,
    "ZWE": 2.6
  },
  "stats": {
    "coverage": 169,
    "min": 0.0,
    "max": 76.7,
    "median": 4.2,
    "quantileBreaks": [
      0.0,
      0.6,
      1.5,
      3.0,
      5.8,
      10.6,
      17.1,
      76.7
    ]
  },
  "formatting": {
    "maximumFractionDigits": 1,
    "suffix": "%"
  },
  "source": {
    "provider": "World Bank",
    "dataset": "World Development Indicators",
    "attribution": "The World Bank",
    "sourceReference": "https://api.worldbank.org/v2/indicator/SM.POP.TOTL.ZS?format=json&per_page=1",
    "valuesReference": "https://api.worldbank.org/v2/country/all/indicator/SM.POP.TOTL.ZS?format=json&per_page=20000&page=1&date=2015%3A2025",
    "license": "Creative Commons Attribution 4.0 International unless specifically labeled otherwise by World Bank metadata",
    "licenseReference": "https://www.worldbank.org/en/about/legal/terms-of-use-for-datasets",
    "retrievedAt": "2026-06-22T18:06:22.805205+00:00",
    "checksum": "128cc7673b919d7799fc84a45c696121cfa1ed81e15d46b55d93b974e820884f",
    "sourceOrganization": "International Migrant Stock, United Nations (UN), publisher: UN Population Division"
  },
  "reviewStatus": "approved",
  "contentVersion": "2026.06.22-exp2-qa1",
  "editorial": {
    "shortHook": "The migrant-share map where Gulf states and small countries pop.",
    "patternNote": "The darkest countries include Qatar, United Arab Emirates, Kuwait, while the lightest include Cuba, China, Madagascar; that contrast is the fastest way to read the international migrant stock pattern.",
    "whyItMatters": "Migrant stock as a population share helps players see where migration has reshaped resident populations.",
    "bestProbeCountries": [
      {
        "iso3": "QAT",
        "reason": "High anchor: this country sits near the darkest end of the map."
      },
      {
        "iso3": "CUB",
        "reason": "Low anchor: this country clarifies the lightest end of the scale."
      },
      {
        "iso3": "IRN",
        "reason": "Middle check: this country helps separate a true pattern from one-off outliers."
      }
    ],
    "commonConfusions": [
      {
        "confusedWithIndicatorCode": "EN.GHG.CO2.PC.CE.AR5",
        "reason": "CO2 emissions per capita overlaps with part of the visible pattern, but the full country spread does not match."
      },
      {
        "confusedWithIndicatorCode": "SH.H2O.SMDW.ZS",
        "reason": "Safely managed drinking water can tempt players because it shares a strong country ranking with this map, but its unit and definition point to a different story."
      },
      {
        "confusedWithIndicatorCode": "NY.GDP.PCAP.CD",
        "reason": "GDP per capita can tempt players because it shares a strong country ranking with this map, but its unit and definition point to a different story."
      }
    ],
    "difficultyReason": "Standard difficulty: the map has readable regional structure, but the best answer still depends on checking the unit and country anchors.",
    "regionalSignals": [
      "Age structure often makes the map readable before labels do.",
      "Compare high-growth and older-population regions."
    ]
  },
  "editorialReview": {
    "status": "daily_eligible",
    "reviewedAt": "2026-06-22",
    "reviewedBy": "Codex editorial QA",
    "qualityScore": 4,
    "funScore": 5,
    "fairnessScore": 4,
    "ambiguityRisk": "medium",
    "dailyEligible": true,
    "practiceEligible": true,
    "challengeEligible": true,
    "expertOnly": false,
    "reviewNotes": [
      "Distinctive map with Gulf, small-state, and migration-hub anchors.",
      "Daily-worthy because it teaches a different demographic pattern than fertility or aging."
    ],
    "acceptableCloseDistractorIds": []
  }
}
